{
"0": "Límite de velocidad (20 km/h)",
  "1": "Límite de velocidad (30 km/h)",
  "2": "Límite de velocidad (50 km/h)",
  "3": "Límite de velocidad (60 km/h)",
  "4": "Límite de velocidad (70 km/h)",
  "5": "Límite de velocidad (80 km/h)",
  "6": "Fin de límite de velocidad (80 km/h)",
  "7": "Límite de velocidad (100 km/h)",
  "8": "Límite de velocidad (120 km/h)",
  "9": "Prohibido adelantar",
  "10": "Prohibido adelantar a camiones",
  "11": "Intersección con prioridad",
  "12": "Carretera con prioridad",
  "13": "Ceder el paso",
  "14": "Detenerse",
  "15": "Prohibido el paso",
  "16": "Prohibido el paso a camiones",
  "17": "Prohibido el paso en una dirección",
  "18": "Peligro general",
  "19": "Curva peligrosa a la izquierda",
  "20": "Curva peligrosa a la derecha",
  "21": "Doble curva (primero a la izquierda)",
  "22": "Baches",
  "23": "Calzada resbaladiza",
  "24": "Estrechamiento por la derecha",
  "25": "Obras",
  "26": "Semáforo",
  "27": "Peatones",
  "28": "Niños",
  "29": "Bicicletas",
  "30": "Hielo/nieve",
  "31": "Animales en la vía",
  "32": "Fin de todas las restricciones",
  "33": "Girar a la derecha obligatorio",
  "34": "Girar a la izquierda obligatorio",
  "35": "Seguir recto obligatorio",
  "36": "Recto o derecha obligatorio",
  "37": "Recto o izquierda obligatorio",
  "38": "Mantenerse a la derecha",
  "39": "Mantenerse a la izquierda",
  "40": "Rotonda obligatoria",
  "41": "Fin de prohibición de adelantar",
  "42": "Fin de prohibición de adelantar a camiones"
}